thirdweb_contract_wrappers-2.0.4-py3.9-nspkg.pth
zero_ex/contract_wrappers/__init__.py
zero_ex/contract_wrappers/bases.py
zero_ex/contract_wrappers/exceptions.py
zero_ex/contract_wrappers/order_conversions.py
zero_ex/contract_wrappers/py.typed
zero_ex/contract_wrappers/tx_params.py
thirdweb_contract_wrappers-2.0.4.dist-info/METADATA
thirdweb_contract_wrappers-2.0.4.dist-info/WHEEL
thirdweb_contract_wrappers-2.0.4.dist-info/namespace_packages.txt
thirdweb_contract_wrappers-2.0.4.dist-info/top_level.txt
thirdweb_contract_wrappers-2.0.4.dist-info/RECORD
