Metadata-Version: 2.1
Name: thirdweb-contract-wrappers
Version: 2.0.4
Summary: Python wrappers for 0x smart contracts
Home-page: https://github.com/0xproject/0x-monorepo/tree/development/python-packages/contract_wrappers
Author: F. Eugene Aumson
Author-email: feuGeneA@users.noreply.github.com
License: Apache 2.0
Keywords: ethereum cryptocurrency 0x decentralized blockchain dex exchange
Platform: UNKNOWN
Classifier: Development Status :: 2 - Pre-Alpha
Classifier: Intended Audience :: Developers
Classifier: Intended Audience :: Financial and Insurance Industry
Classifier: License :: OSI Approved :: Apache Software License
Classifier: Natural Language :: English
Classifier: Operating System :: OS Independent
Classifier: Programming Language :: Python
Classifier: Programming Language :: Python :: 3 :: Only
Classifier: Programming Language :: Python :: 3.6
Classifier: Programming Language :: Python :: 3.7
Classifier: Topic :: Internet :: WWW/HTTP
Classifier: Topic :: Office/Business :: Financial
Classifier: Topic :: Other/Nonlisted Topic
Classifier: Topic :: Security :: Cryptography
Classifier: Topic :: Software Development :: Libraries
Classifier: Topic :: Utilities
Requires-Python: >=3.6, <4
Provides-Extra: dev
